artd_packages/__init__.py
artd_packages/asgi.py
artd_packages/settings.py
artd_packages/urls.py
artd_packages/wsgi.py
artd_price_list/__init__.py
artd_price_list/admin.py
artd_price_list/apps.py
artd_price_list/forms.py
artd_price_list/models.py
artd_price_list/signals.py
artd_price_list/locale/en/LC_MESSAGES/django.po
artd_price_list/locale/es/LC_MESSAGES/django.po
artd_price_list/migrations/0001_initial.py
artd_price_list/migrations/0002_pricelist_external_id_pricelist_source_and_more.py
artd_price_list/migrations/0003_alter_pricelist_partner_alter_pricelist_product_and_more.py
artd_price_list/migrations/0004_alter_pricelist_special_price_from_and_more.py
artd_price_list/migrations/0005_alter_pricelist_special_price_from_and_more.py
artd_price_list/migrations/0006_alter_pricelist_unique_together.py
artd_price_list/migrations/0007_pricelist_description_pricelistlog_description.py
artd_price_list/migrations/__init__.py
artd_price_list/utils/__init__.py
artd_price_list/utils/generators.py
artd_price_list-1.0.13.dist-info/LICENSE
artd_price_list-1.0.13.dist-info/METADATA
artd_price_list-1.0.13.dist-info/WHEEL
artd_price_list-1.0.13.dist-info/top_level.txt
artd_price_list-1.0.13.dist-info/RECORD
